http_wizz/__init__.py
http_wizz/client.py
http_wizz/py.typed
http_wizz/ratelimit.py
http_wizz/session.py
http_wizz-1.0.2.dist-info/LICENSE
http_wizz-1.0.2.dist-info/METADATA
http_wizz-1.0.2.dist-info/WHEEL
http_wizz-1.0.2.dist-info/top_level.txt
http_wizz-1.0.2.dist-info/RECORD
