Metadata-Version: 2.1
Name: http-wizz
Version: 1.0.2
Summary: The missing rate-limit wrapper for aiohttp. Effortlessly handle 429s, Retry-After headers, and domain throttling for scraping and data pipelines.
Author: Gemini User
License: MIT
Project-URL: Homepage, https://github.com/tommckenna1/http-wizz
Project-URL: Bug Tracker, https://github.com/tommckenna1/http-wizz/issues
Project-URL: Source Code, https://github.com/tommckenna1/http-wizz
Keywords: api-client,data-pipeline,batch-processing,geocoding,web-scraping,rate-limit,backoff,throttling,aiohttp,asyncio,token-bucket,retry-after,429
Classifier: Development Status :: 5 - Production/Stable
Classifier: Intended Audience :: Developers
Classifier: License :: OSI Approved :: MIT License
Classifier: Programming Language :: Python :: 3
Classifier: Programming Language :: Python :: 3.7
Classifier: Programming Language :: Python :: 3.8
Classifier: Programming Language :: Python :: 3.9
Classifier: Programming Language :: Python :: 3.10
Classifier: Programming Language :: Python :: 3.11
Classifier: Topic :: Internet :: WWW/HTTP
Classifier: Topic :: Internet :: WWW/HTTP :: Indexing/Search
Classifier: Topic :: Software Development :: Libraries :: Python Modules
Classifier: Framework :: AsyncIO
Classifier: Operating System :: OS Independent
Requires-Python: >=3.7
License-File: LICENSE
Requires-Dist: aiohttp>=3.8.0
